neuron_assistant/__init__.py
neuron_assistant/assistant.py
neuron_assistant/config.json
neuron_assistant/config.sig
neuron_assistant/public_key.pem
neuron_assistant-0.1.0.dist-info/licenses/License
neuron_assistant-0.1.0.dist-info/METADATA
neuron_assistant-0.1.0.dist-info/WHEEL
neuron_assistant-0.1.0.dist-info/entry_points.txt
neuron_assistant-0.1.0.dist-info/top_level.txt
neuron_assistant-0.1.0.dist-info/RECORD
