Metadata-Version: 2.4
Name: neuron_assistant
Version: 0.1.0
Summary: Neuron AI assistant by Dev Patel
Author: Dev Patel
Requires-Python: >=3.8
License-File: License
Requires-Dist: llama-cpp-python
Requires-Dist: huggingface-hub
Requires-Dist: cryptography
Requires-Dist: torch
Requires-Dist: psutil
Dynamic: author
Dynamic: license-file
Dynamic: requires-dist
Dynamic: requires-python
Dynamic: summary
